rre/__init__.py
rre/regexes.json
rre/regular_regexes.py
rre-0.0.6.dist-info/LICENSE
rre-0.0.6.dist-info/METADATA
rre-0.0.6.dist-info/WHEEL
rre-0.0.6.dist-info/top_level.txt
rre-0.0.6.dist-info/RECORD
