Metadata-Version: 2.1
Name: rre
Version: 0.0.6
Summary: Simplify the usage of common regexes
Home-page: https://github.com/upshiftbe/regular-regexes
Author: Upshift
Author-email: hello@upshift.be
Project-URL: Bug Tracker, https://github.com/upshiftbe/regular-regexes/issues
Classifier: Programming Language :: Python :: 3
Classifier: License :: OSI Approved :: MIT License
Classifier: Operating System :: OS Independent
Requires-Python: >=3.6
License-File: LICENSE
